pyAMT/__init__.py
pyAMT/main.py
pyAMT-0.0.3.dist-info/LICENSE
pyAMT-0.0.3.dist-info/METADATA
pyAMT-0.0.3.dist-info/WHEEL
pyAMT-0.0.3.dist-info/top_level.txt
pyAMT-0.0.3.dist-info/RECORD
