Metadata-Version: 2.1
Name: pyAMT
Version: 0.0.3
Summary: An unofficial wrapper for AMT Genova undocumented API
Home-page: https://github.com/rcastellotti/pyAMT
Author: Roberto Castellotti
Author-email: me@rcastellotti.dev
License: UNKNOWN
Platform: UNKNOWN
Classifier: Programming Language :: Python :: 3
Classifier: License :: OSI Approved :: MIT License
Classifier: Operating System :: OS Independent
Requires-Python: >=3.9
License-File: LICENSE
Requires-Dist: requests
Requires-Dist: xmltodict
